percolation/__init__.py
percolation/ds.py
percolation/grid.py
percolation/monte_carlo.py
percolation/naive.py
percolation_threshold-0.0.2.dist-info/LICENSE
percolation_threshold-0.0.2.dist-info/METADATA
percolation_threshold-0.0.2.dist-info/WHEEL
percolation_threshold-0.0.2.dist-info/top_level.txt
percolation_threshold-0.0.2.dist-info/RECORD
