Metadata-Version: 2.1
Name: percolation-threshold
Version: 0.0.2
Summary: Computational tool to calculate percolation threshold for various lattices
Home-page: https://github.com/MissingBrainException/PercolationThreshold
Author: MissingBrainException, Khadir Mohamed Islam, Abdennour Slimane
Author-email: muhammad.masud.1997@gmail.com, islam.islam.khadir6@gmail.com, slimaneabdennourphysics@gmail.com
License: UNKNOWN
Platform: UNKNOWN
Classifier: Programming Language :: Python :: 3
Classifier: License :: OSI Approved :: MIT License
Classifier: Operating System :: OS Independent
Classifier: Topic :: Scientific/Engineering :: Physics
Requires-Python: >=3.3
Requires-Dist: matplotlib
Requires-Dist: numpy
Requires-Dist: psutil
